{"lands":{"autotiles":[{"k":[14,0,0,15,0],"v":{"id":1,"t":[1,1],"tid":324}},{"k":[15,0,0,14,0],"v":{"id":1,"t":[1,1],"tid":370}},{"k":[15,0,0,15,0],"v":{"id":1,"t":[1,1],"tid":372}},{"k":[11,0,0,14,0],"v":{"id":1,"t":[1,1],"tid":318}},{"k":[12,0,0,13,0],"v":{"id":1,"t":[1,1],"tid":318}},{"k":[10,0,0,15,0],"v":{"id":1,"t":[1,1],"tid":324}},{"k":[15,0,0,10,0],"v":{"id":1,"t":[1,1],"tid":370}},{"k":[13,0,0,12,0],"v":{"id":1,"t":[1,1],"tid":318}},{"k":[14,0,0,11,0],"v":{"id":1,"t":[1,1],"tid":318}},{"k":[12,0,0,14,0],"v":{"id":1,"t":[1,1],"tid":318}},{"k":[11,0,0,15,0],"v":{"id":1,"t":[1,1],"tid":324}},{"k":[15,0,0,11,0],"v":{"id":1,"t":[1,1],"tid":370}},{"k":[13,0,0,13,0],"v":{"id":1,"t":[1,1],"tid":318}},{"k":[14,0,0,12,0],"v":{"id":1,"t":[1,1],"tid":318}},{"k":[12,0,0,15,0],"v":{"id":1,"t":[1,1],"tid":324}},{"k":[15,0,0,12,0],"v":{"id":1,"t":[1,1],"tid":370}},{"k":[13,0,0,14,0],"v":{"id":1,"t":[1,1],"tid":318}},{"k":[14,0,0,13,0],"v":{"id":1,"t":[1,1],"tid":318}},{"k":[13,0,0,15,0],"v":{"id":1,"t":[1,1],"tid":324}},{"k":[14,0,0,14,0],"v":{"id":1,"t":[1,1],"tid":318}},{"k":[15,0,0,13,0],"v":{"id":1,"t":[1,1],"tid":370}},{"k":[7,0,0,6,0],"v":{"id":1,"t":[1,1],"tid":225}},{"k":[2,0,0,11,0],"v":{"id":1,"t":[1,1],"tid":159}},{"k":[8,0,0,6,0],"v":{"id":1,"t":[1,1],"tid":471}},{"k":[7,0,0,7,0],"v":{"id":1,"t":[1,1],"tid":584}},{"k":[7,0,0,8,0],"v":{"id":1,"t":[1,1],"tid":584}},{"k":[9,0,0,6,0],"v":{"id":1,"t":[1,1],"tid":471}},{"k":[8,0,0,7,0],"v":{"id":1,"t":[1,1],"tid":318}},{"k":[7,0,0,9,0],"v":{"id":1,"t":[1,1],"tid":584}},{"k":[8,0,0,8,0],"v":{"id":1,"t":[1,1],"tid":318}},{"k":[10,0,0,6,0],"v":{"id":1,"t":[1,1],"tid":471}},{"k":[9,0,0,7,0],"v":{"id":1,"t":[1,1],"tid":318}},{"k":[6,0,0,10,0],"v":{"id":1,"t":[1,1],"tid":225}},{"k":[14,0,0,7,0],"v":{"id":1,"t":[1,1],"tid":471}},{"k":[13,0,0,8,0],"v":{"id":1,"t":[1,1],"tid":318}},{"k":[7,0,0,14,0],"v":{"id":1,"t":[1,1],"tid":584}},{"k":[8,0,0,13,0],"v":{"id":1,"t":[1,1],"tid":318}},{"k":[9,0,0,12,0],"v":{"id":1,"t":[1,1],"tid":318}},{"k":[10,0,0,11,0],"v":{"id":1,"t":[1,1],"tid":318}},{"k":[12,0,0,9,0],"v":{"id":1,"t":[1,1],"tid":318}},{"k":[11,0,0,10,0],"v":{"id":1,"t":[1,1],"tid":318}},{"k":[7,0,0,15,0],"v":{"id":1,"t":[1,1],"tid":570}},{"k":[15,0,0,7,0],"v":{"id":1,"t":[1,1],"tid":423}},{"k":[14,0,0,8,0],"v":{"id":1,"t":[1,1],"tid":318}},{"k":[8,0,0,14,0],"v":{"id":1,"t":[1,1],"tid":318}},{"k":[9,0,0,13,0],"v":{"id":1,"t":[1,1],"tid":318}},{"k":[10,0,0,12,0],"v":{"id":1,"t":[1,1],"tid":318}},{"k":[11,0,0,11,0],"v":{"id":1,"t":[1,1],"tid":318}},{"k":[13,0,0,9,0],"v":{"id":1,"t":[1,1],"tid":318}},{"k":[12,0,0,10,0],"v":{"id":1,"t":[1,1],"tid":318}},{"k":[10,0,0,13,0],"v":{"id":1,"t":[1,1],"tid":318}},{"k":[8,0,0,15,0],"v":{"id":1,"t":[1,1],"tid":324}},{"k":[15,0,0,8,0],"v":{"id":1,"t":[1,1],"tid":370}},{"k":[13,0,0,10,0],"v":{"id":1,"t":[1,1],"tid":318}},{"k":[14,0,0,9,0],"v":{"id":1,"t":[1,1],"tid":318}},{"k":[9,0,0,14,0],"v":{"id":1,"t":[1,1],"tid":318}},{"k":[12,0,0,11,0],"v":{"id":1,"t":[1,1],"tid":318}},{"k":[11,0,0,12,0],"v":{"id":1,"t":[1,1],"tid":318}},{"k":[11,0,0,13,0],"v":{"id":1,"t":[1,1],"tid":318}},{"k":[10,0,0,14,0],"v":{"id":1,"t":[1,1],"tid":318}},{"k":[9,0,0,15,0],"v":{"id":1,"t":[1,1],"tid":324}},{"k":[15,0,0,9,0],"v":{"id":1,"t":[1,1],"tid":370}},{"k":[13,0,0,11,0],"v":{"id":1,"t":[1,1],"tid":318}},{"k":[14,0,0,10,0],"v":{"id":1,"t":[1,1],"tid":318}},{"k":[12,0,0,12,0],"v":{"id":1,"t":[1,1],"tid":318}},{"k":[9,0,0,8,0],"v":{"id":1,"t":[1,1],"tid":318}},{"k":[7,0,0,10,0],"v":{"id":1,"t":[1,1],"tid":62}},{"k":[8,0,0,9,0],"v":{"id":1,"t":[1,1],"tid":318}},{"k":[10,0,0,7,0],"v":{"id":1,"t":[1,1],"tid":318}},{"k":[11,0,0,6,0],"v":{"id":1,"t":[1,1],"tid":471}},{"k":[6,0,0,11,0],"v":{"id":1,"t":[1,1],"tid":570}},{"k":[7,0,0,11,0],"v":{"id":1,"t":[1,1],"tid":308}},{"k":[8,0,0,10,0],"v":{"id":1,"t":[1,1],"tid":318}},{"k":[9,0,0,9,0],"v":{"id":1,"t":[1,1],"tid":318}},{"k":[10,0,0,8,0],"v":{"id":1,"t":[1,1],"tid":318}},{"k":[11,0,0,7,0],"v":{"id":1,"t":[1,1],"tid":318}},{"k":[12,0,0,6,0],"v":{"id":1,"t":[1,1],"tid":423}},{"k":[7,0,0,12,0],"v":{"id":1,"t":[1,1],"tid":584}},{"k":[8,0,0,11,0],"v":{"id":1,"t":[1,1],"tid":318}},{"k":[9,0,0,10,0],"v":{"id":1,"t":[1,1],"tid":318}},{"k":[10,0,0,9,0],"v":{"id":1,"t":[1,1],"tid":318}},{"k":[11,0,0,8,0],"v":{"id":1,"t":[1,1],"tid":318}},{"k":[12,0,0,7,0],"v":{"id":1,"t":[1,1],"tid":268}},{"k":[12,0,0,8,0],"v":{"id":1,"t":[1,1],"tid":318}},{"k":[7,0,0,13,0],"v":{"id":1,"t":[1,1],"tid":584}},{"k":[8,0,0,12,0],"v":{"id":1,"t":[1,1],"tid":318}},{"k":[9,0,0,11,0],"v":{"id":1,"t":[1,1],"tid":318}},{"k":[11,0,0,9,0],"v":{"id":1,"t":[1,1],"tid":318}},{"k":[13,0,0,7,0],"v":{"id":1,"t":[1,1],"tid":471}},{"k":[10,0,0,10,0],"v":{"id":1,"t":[1,1],"tid":318}}],"floors":[{"k":[15,3,0,11,0],"v":{"t":[0,0]}},{"k":[11,3,0,15,0],"v":{"t":[0,0]}},{"k":[10,4,0,15,0],"v":{"t":[0,0]}},{"k":[15,4,0,10,0],"v":{"t":[0,0]}},{"k":[15,3,0,12,0],"v":{"t":[0,0]}},{"k":[12,3,0,15,0],"v":{"t":[0,0]}},{"k":[11,4,0,15,0],"v":{"t":[0,0]}},{"k":[15,4,0,11,0],"v":{"t":[0,0]}},{"k":[15,3,0,13,0],"v":{"t":[0,0]}},{"k":[13,3,0,15,0],"v":{"t":[0,0]}},{"k":[12,4,0,15,0],"v":{"t":[0,0]}},{"k":[15,4,0,12,0],"v":{"t":[0,0]}},{"k":[15,3,0,14,0],"v":{"t":[0,0]}},{"k":[14,3,0,15,0],"v":{"t":[0,0]}},{"k":[13,4,0,15,0],"v":{"t":[0,0]}},{"k":[15,4,0,13,0],"v":{"t":[0,0]}},{"k":[15,3,0,7,0],"v":{"t":[0,0]}},{"k":[7,3,0,15,0],"v":{"t":[0,0]}},{"k":[15,4,0,6,0],"v":{"t":[0,0]}},{"k":[6,4,0,15,0],"v":{"t":[0,0]}},{"k":[15,3,0,8,0],"v":{"t":[0,0]}},{"k":[8,3,0,15,0],"v":{"t":[0,0]}},{"k":[15,4,0,7,0],"v":{"t":[0,0]}},{"k":[7,4,0,15,0],"v":{"t":[0,0]}},{"k":[15,3,0,9,0],"v":{"t":[0,0]}},{"k":[9,3,0,15,0],"v":{"t":[0,0]}},{"k":[8,4,0,15,0],"v":{"t":[0,0]}},{"k":[15,4,0,8,0],"v":{"t":[0,0]}},{"k":[15,3,0,10,0],"v":{"t":[0,0]}},{"k":[10,3,0,15,0],"v":{"t":[0,0]}},{"k":[9,4,0,15,0],"v":{"t":[0,0]}},{"k":[15,4,0,9,0],"v":{"t":[0,0]}},{"k":[15,3,0,15,0],"v":{"t":[0,0]}},{"k":[14,4,0,15,0],"v":{"t":[0,0]}},{"k":[15,4,0,14,0],"v":{"t":[0,0]}},{"k":[15,4,0,15,0],"v":{"t":[0,0]}},{"k":[0,3,0,2,0],"v":{"t":[0,0]}},{"k":[2,3,0,0,0],"v":{"t":[0,0]}},{"k":[0,0,0,5,0],"v":{"t":[1,1]}},{"k":[1,0,0,4,0],"v":{"t":[0,1]}},{"k":[2,0,0,3,0],"v":{"t":[0,1]}},{"k":[3,0,0,2,0],"v":{"t":[0,1]}},{"k":[4,0,0,1,0],"v":{"t":[0,1]}},{"k":[1,1,0,3,0],"v":{"t":[0,0]}},{"k":[1,4,0,0,0],"v":{"t":[0,0]}},{"k":[0,4,0,1,0],"v":{"t":[0,0]}},{"k":[0,3,0,3,0],"v":{"t":[0,0]}},{"k":[3,3,0,0,0],"v":{"t":[0,0]}},{"k":[6,0,0,0,0],"v":{"t":[1,1]}},{"k":[0,0,0,6,0],"v":{"t":[1,1]}},{"k":[1,0,0,5,0],"v":{"t":[0,1]}},{"k":[3,0,0,3,0],"v":{"t":[0,1]}},{"k":[2,0,0,4,0],"v":{"t":[0,1]}},{"k":[4,0,0,2,0],"v":{"t":[0,1]}},{"k":[5,0,0,1,0],"v":{"t":[0,1]}},{"k":[1,1,0,4,0],"v":{"t":[0,0]}},{"k":[2,4,0,0,0],"v":{"t":[0,0]}},{"k":[0,4,0,2,0],"v":{"t":[0,0]}},{"k":[0,3,0,4,0],"v":{"t":[0,0]}},{"k":[4,3,0,0,0],"v":{"t":[0,0]}},{"k":[1,0,0,6,0],"v":{"t":[1,1]}},{"k":[2,0,0,5,0],"v":{"t":[0,1]}},{"k":[4,0,0,3,0],"v":{"t":[0,1]}},{"k":[3,0,0,4,0],"v":{"t":[0,1]}},{"k":[5,0,0,2,0],"v":{"t":[0,1]}},{"k":[6,0,0,1,0],"v":{"t":[0,1]}},{"k":[3,4,0,0,0],"v":{"t":[0,0]}},{"k":[0,4,0,3,0],"v":{"t":[0,0]}},{"k":[0,3,0,5,0],"v":{"t":[0,0]}},{"k":[5,3,0,0,0],"v":{"t":[0,0]}},{"k":[1,0,0,7,0],"v":{"t":[1,1]}},{"k":[2,0,0,6,0],"v":{"t":[1,1]}},{"k":[3,0,0,5,0],"v":{"t":[0,1]}},{"k":[4,0,0,4,0],"v":{"t":[0,1]}},{"k":[6,0,0,2,0],"v":{"t":[0,1]}},{"k":[5,0,0,3,0],"v":{"t":[0,1]}},{"k":[7,0,0,1,0],"v":{"t":[0,1]}},{"k":[4,4,0,0,0],"v":{"t":[0,0]}},{"k":[0,4,0,4,0],"v":{"t":[0,0]}},{"k":[1,0,0,1,0],"v":{"t":[0,1]}},{"k":[0,3,0,0,0],"v":{"t":[0,0]}},{"k":[1,0,0,2,0],"v":{"t":[0,1]}},{"k":[2,0,0,1,0],"v":{"t":[0,1]}},{"k":[1,1,0,1,0],"v":{"t":[0,0]}},{"k":[0,3,0,1,0],"v":{"t":[0,0]}},{"k":[1,3,0,0,0],"v":{"t":[0,0]}},{"k":[1,0,0,3,0],"v":{"t":[0,1]}},{"k":[3,0,0,1,0],"v":{"t":[0,1]}},{"k":[2,0,0,2,0],"v":{"t":[0,1]}},{"k":[1,1,0,2,0],"v":{"t":[0,0]}},{"k":[0,4,0,0,0],"v":{"t":[0,0]}},{"k":[0,3,0,10,0],"v":{"t":[0,0]}},{"k":[10,3,0,0,0],"v":{"t":[0,0]}},{"k":[5,3,0,5,0],"v":{"t":[0,0]}},{"k":[4,0,0,9,0],"v":{"t":[1,1]}},{"k":[5,0,0,8,0],"v":{"t":[1,1]}},{"k":[6,0,0,7,0],"v":{"t":[1,1]}},{"k":[1,0,0,12,0],"v":{"t":[6,3]}},{"k":[3,0,0,10,0],"v":{"t":[1,1]}},{"k":[8,0,0,5,0],"v":{"t":[0,1]}},{"k":[9,0,0,4,0],"v":{"t":[0,1]}},{"k":[11,0,0,2,0],"v":{"t":[0,1]}},{"k":[12,0,0,1,0],"v":{"t":[0,1]}},{"k":[13,0,0,0,0],"v":{"t":[0,1]}},{"k":[9,4,0,0,0],"v":{"t":[0,0]}},{"k":[0,4,0,9,0],"v":{"t":[0,0]}},{"k":[4,4,0,5,0],"v":{"t":[0,0]}},{"k":[0,3,0,11,0],"v":{"t":[0,0]}},{"k":[11,3,0,0,0],"v":{"t":[0,0]}},{"k":[10,3,0,1,0],"v":{"t":[0,0]}},{"k":[6,3,0,5,0],"v":{"t":[0,0]}},{"k":[3,0,0,11,0],"v":{"t":[1,1]}},{"k":[4,0,0,10,0],"v":{"t":[1,1]}},{"k":[6,0,0,8,0],"v":{"t":[1,1]}},{"k":[5,0,0,9,0],"v":{"t":[1,1]}},{"k":[1,0,0,13,0],"v":{"t":[6,4]}},{"k":[2,0,0,12,0],"v":{"t":[7,3]}},{"k":[9,0,0,5,0],"v":{"t":[0,1]}},{"k":[11,0,0,3,0],"v":{"t":[0,1]}},{"k":[12,0,0,2,0],"v":{"t":[0,1]}},{"k":[13,0,0,1,0],"v":{"t":[0,1]}},{"k":[14,0,0,0,0],"v":{"t":[0,1]}},{"k":[0,4,0,10,0],"v":{"t":[0,0]}},{"k":[5,4,0,5,0],"v":{"t":[0,0]}},{"k":[10,4,0,0,0],"v":{"t":[0,0]}},{"k":[0,3,0,12,0],"v":{"t":[0,0]}},{"k":[12,3,0,0,0],"v":{"t":[0,0]}},{"k":[10,3,0,2,0],"v":{"t":[0,0]}},{"k":[7,3,0,5,0],"v":{"t":[0,0]}},{"k":[6,3,0,6,0],"v":{"t":[0,0]}},{"k":[4,0,0,11,0],"v":{"t":[1,1]}},{"k":[6,0,0,9,0],"v":{"t":[1,1]}},{"k":[5,0,0,10,0],"v":{"t":[1,1]}},{"k":[3,0,0,12,0],"v":{"t":[7,3]}},{"k":[1,0,0,14,0],"v":{"t":[6,5]}},{"k":[2,0,0,13,0],"v":{"t":[7,4]}},{"k":[11,0,0,4,0],"v":{"t":[0,1]}},{"k":[13,0,0,2,0],"v":{"t":[0,1]}},{"k":[12,0,0,3,0],"v":{"t":[0,1]}},{"k":[15,0,0,0,0],"v":{"t":[0,1]}},{"k":[14,0,0,1,0],"v":{"t":[0,1]}},{"k":[11,4,0,0,0],"v":{"t":[0,0]}},{"k":[10,4,0,1,0],"v":{"t":[0,0]}},{"k":[0,4,0,11,0],"v":{"t":[0,0]}},{"k":[6,4,0,5,0],"v":{"t":[0,0]}},{"k":[0,3,0,13,0],"v":{"t":[0,0]}},{"k":[13,3,0,0,0],"v":{"t":[0,0]}},{"k":[10,3,0,3,0],"v":{"t":[0,0]}},{"k":[6,3,0,7,0],"v":{"t":[0,0]}},{"k":[4,0,0,12,0],"v":{"t":[1,1]}},{"k":[5,0,0,11,0],"v":{"t":[1,1]}},{"k":[3,0,0,13,0],"v":{"t":[7,4]}},{"k":[2,0,0,14,0],"v":{"t":[7,5]}},{"k":[11,0,0,5,0],"v":{"t":[0,1]}},{"k":[12,0,0,4,0],"v":{"t":[0,1]}},{"k":[14,0,0,2,0],"v":{"t":[0,1]}},{"k":[13,0,0,3,0],"v":{"t":[0,1]}},{"k":[12,4,0,0,0],"v":{"t":[0,0]}},{"k":[10,4,0,2,0],"v":{"t":[0,0]}},{"k":[0,4,0,12,0],"v":{"t":[0,0]}},{"k":[6,4,0,6,0],"v":{"t":[0,0]}},{"k":[7,4,0,5,0],"v":{"t":[0,0]}},{"k":[0,3,0,6,0],"v":{"t":[0,0]}},{"k":[6,3,0,0,0],"v":{"t":[0,0]}},{"k":[1,3,0,5,0],"v":{"t":[0,0]}},{"k":[1,0,0,8,0],"v":{"t":[1,1]}},{"k":[2,0,0,7,0],"v":{"t":[1,1]}},{"k":[3,0,0,6,0],"v":{"t":[1,1]}},{"k":[4,0,0,5,0],"v":{"t":[0,1]}},{"k":[5,0,0,4,0],"v":{"t":[0,1]}},{"k":[7,0,0,2,0],"v":{"t":[0,1]}},{"k":[6,0,0,3,0],"v":{"t":[0,1]}},{"k":[8,0,0,1,0],"v":{"t":[0,1]}},{"k":[5,4,0,0,0],"v":{"t":[0,0]}},{"k":[0,4,0,5,0],"v":{"t":[0,0]}},{"k":[0,3,0,7,0],"v":{"t":[0,0]}},{"k":[7,3,0,0,0],"v":{"t":[0,0]}},{"k":[2,3,0,5,0],"v":{"t":[0,0]}},{"k":[5,0,0,5,0],"v":{"t":[1,1]}},{"k":[4,0,0,6,0],"v":{"t":[1,1]}},{"k":[1,0,0,9,0],"v":{"t":[1,1]}},{"k":[3,0,0,7,0],"v":{"t":[1,1]}},{"k":[2,0,0,8,0],"v":{"t":[1,1]}},{"k":[9,0,0,1,0],"v":{"t":[0,1]}},{"k":[6,0,0,4,0],"v":{"t":[0,1]}},{"k":[8,0,0,2,0],"v":{"t":[0,1]}},{"k":[7,0,0,3,0],"v":{"t":[0,1]}},{"k":[1,1,0,8,0],"v":{"t":[0,0]}},{"k":[6,4,0,0,0],"v":{"t":[0,0]}},{"k":[0,4,0,6,0],"v":{"t":[0,0]}},{"k":[1,4,0,5,0],"v":{"t":[0,0]}},{"k":[0,3,0,8,0],"v":{"t":[0,0]}},{"k":[8,3,0,0,0],"v":{"t":[0,0]}},{"k":[3,3,0,5,0],"v":{"t":[0,0]}},{"k":[4,0,0,7,0],"v":{"t":[1,1]}},{"k":[5,0,0,6,0],"v":{"t":[1,1]}},{"k":[6,0,0,5,0],"v":{"t":[1,1]}},{"k":[1,0,0,10,0],"v":{"t":[1,1]}},{"k":[2,0,0,9,0],"v":{"t":[1,1]}},{"k":[3,0,0,8,0],"v":{"t":[1,1]}},{"k":[7,0,0,4,0],"v":{"t":[0,1]}},{"k":[9,0,0,2,0],"v":{"t":[0,1]}},{"k":[8,0,0,3,0],"v":{"t":[0,1]}},{"k":[1,1,0,9,0],"v":{"t":[0,0]}},{"k":[7,4,0,0,0],"v":{"t":[0,0]}},{"k":[0,4,0,7,0],"v":{"t":[0,0]}},{"k":[2,4,0,5,0],"v":{"t":[0,0]}},{"k":[0,3,0,9,0],"v":{"t":[0,0]}},{"k":[9,3,0,0,0],"v":{"t":[0,0]}},{"k":[4,3,0,5,0],"v":{"t":[0,0]}},{"k":[4,0,0,8,0],"v":{"t":[1,1]}},{"k":[5,0,0,7,0],"v":{"t":[1,1]}},{"k":[6,0,0,6,0],"v":{"t":[1,1]}},{"k":[1,0,0,11,0],"v":{"t":[1,1]}},{"k":[2,0,0,10,0],"v":{"t":[1,1]}},{"k":[3,0,0,9,0],"v":{"t":[1,1]}},{"k":[8,0,0,4,0],"v":{"t":[0,1]}},{"k":[9,0,0,3,0],"v":{"t":[0,1]}},{"k":[11,0,0,1,0],"v":{"t":[0,1]}},{"k":[12,0,0,0,0],"v":{"t":[0,1]}},{"k":[8,4,0,0,0],"v":{"t":[0,0]}},{"k":[0,4,0,8,0],"v":{"t":[0,0]}},{"k":[3,4,0,5,0],"v":{"t":[0,0]}},{"k":[15,3,0,3,0],"v":{"t":[0,0]}},{"k":[3,3,0,15,0],"v":{"t":[0,0]}},{"k":[12,3,0,6,0],"v":{"t":[0,0]}},{"k":[6,3,0,12,0],"v":{"t":[0,0]}},{"k":[15,4,0,2,0],"v":{"t":[0,0]}},{"k":[11,4,0,6,0],"v":{"t":[0,0]}},{"k":[2,4,0,15,0],"v":{"t":[0,0]}},{"k":[15,3,0,4,0],"v":{"t":[0,0]}},{"k":[4,3,0,15,0],"v":{"t":[0,0]}},{"k":[6,3,0,13,0],"v":{"t":[0,0]}},{"k":[15,4,0,3,0],"v":{"t":[0,0]}},{"k":[3,4,0,15,0],"v":{"t":[0,0]}},{"k":[12,4,0,6,0],"v":{"t":[0,0]}},{"k":[6,4,0,12,0],"v":{"t":[0,0]}},{"k":[15,3,0,5,0],"v":{"t":[0,0]}},{"k":[5,3,0,15,0],"v":{"t":[0,0]}},{"k":[6,3,0,14,0],"v":{"t":[0,0]}},{"k":[15,4,0,4,0],"v":{"t":[0,0]}},{"k":[4,4,0,15,0],"v":{"t":[0,0]}},{"k":[6,4,0,13,0],"v":{"t":[0,0]}},{"k":[15,3,0,6,0],"v":{"t":[0,0]}},{"k":[6,3,0,15,0],"v":{"t":[0,0]}},{"k":[15,4,0,5,0],"v":{"t":[0,0]}},{"k":[5,4,0,15,0],"v":{"t":[0,0]}},{"k":[6,4,0,14,0],"v":{"t":[0,0]}},{"k":[0,3,0,14,0],"v":{"t":[0,0]}},{"k":[14,3,0,0,0],"v":{"t":[0,0]}},{"k":[10,3,0,4,0],"v":{"t":[0,0]}},{"k":[6,3,0,8,0],"v":{"t":[0,0]}},{"k":[2,0,0,15,0],"v":{"t":[1,1]}},{"k":[4,0,0,13,0],"v":{"t":[1,1]}},{"k":[5,0,0,12,0],"v":{"t":[1,1]}},{"k":[3,0,0,14,0],"v":{"t":[7,5]}},{"k":[12,0,0,5,0],"v":{"t":[0,1]}},{"k":[14,0,0,3,0],"v":{"t":[0,1]}},{"k":[13,0,0,4,0],"v":{"t":[0,1]}},{"k":[13,4,0,0,0],"v":{"t":[0,0]}},{"k":[10,4,0,3,0],"v":{"t":[0,0]}},{"k":[0,4,0,13,0],"v":{"t":[0,0]}},{"k":[6,4,0,7,0],"v":{"t":[0,0]}},{"k":[0,3,0,15,0],"v":{"t":[0,0]}},{"k":[15,3,0,0,0],"v":{"t":[0,0]}},{"k":[10,3,0,5,0],"v":{"t":[0,0]}},{"k":[6,3,0,9,0],"v":{"t":[0,0]}},{"k":[3,0,0,15,0],"v":{"t":[1,1]}},{"k":[4,0,0,14,0],"v":{"t":[1,1]}},{"k":[5,0,0,13,0],"v":{"t":[1,1]}},{"k":[13,0,0,5,0],"v":{"t":[0,1]}},{"k":[14,0,0,4,0],"v":{"t":[0,1]}},{"k":[14,4,0,0,0],"v":{"t":[0,0]}},{"k":[10,4,0,4,0],"v":{"t":[0,0]}},{"k":[0,4,0,14,0],"v":{"t":[0,0]}},{"k":[6,4,0,8,0],"v":{"t":[0,0]}},{"k":[15,3,0,1,0],"v":{"t":[0,0]}},{"k":[1,3,0,15,0],"v":{"t":[0,0]}},{"k":[10,3,0,6,0],"v":{"t":[0,0]}},{"k":[4,0,0,15,0],"v":{"t":[1,1]}},{"k":[5,0,0,14,0],"v":{"t":[1,1]}},{"k":[13,0,0,6,0],"v":{"t":[0,1]}},{"k":[14,0,0,5,0],"v":{"t":[0,1]}},{"k":[10,4,0,5,0],"v":{"t":[0,0]}},{"k":[0,4,0,15,0],"v":{"t":[0,0]}},{"k":[15,4,0,0,0],"v":{"t":[0,0]}},{"k":[6,4,0,9,0],"v":{"t":[0,0]}},{"k":[15,3,0,2,0],"v":{"t":[0,0]}},{"k":[2,3,0,15,0],"v":{"t":[0,0]}},{"k":[11,3,0,6,0],"v":{"t":[0,0]}},{"k":[14,0,0,6,0],"v":{"t":[0,1]}},{"k":[15,4,0,1,0],"v":{"t":[0,0]}},{"k":[1,4,0,15,0],"v":{"t":[0,0]}},{"k":[10,4,0,6,0],"v":{"t":[0,0]}}]},"moun":{"a":[{"k":[15,0,0,14,0],"v":{"b":true,"hs":3,"sid":16,"t":true}},{"k":[14,0,0,15,0],"v":{"hs":3,"l":true,"r":true,"sid":16}},{"k":[11,3,0,15,0],"v":{"l":true,"r":true,"sid":16}},{"k":[15,3,0,11,0],"v":{"b":true,"sid":16,"t":true}},{"k":[15,0,0,15,0],"v":{"hs":3,"l":true,"sid":16,"t":true}},{"k":[12,3,0,15,0],"v":{"l":true,"r":true,"sid":16}},{"k":[15,3,0,12,0],"v":{"b":true,"sid":16,"t":true}},{"k":[13,3,0,15,0],"v":{"l":true,"r":true,"sid":16}},{"k":[15,3,0,13,0],"v":{"b":true,"sid":16,"t":true}},{"k":[14,3,0,15,0],"v":{"l":true,"r":true,"sid":16}},{"k":[15,3,0,14,0],"v":{"b":true,"sid":16,"t":true}},{"k":[15,0,0,10,0],"v":{"b":true,"hs":3,"sid":16,"t":true}},{"k":[10,0,0,15,0],"v":{"hs":3,"l":true,"r":true,"sid":16}},{"k":[15,3,0,7,0],"v":{"b":true,"sid":16,"t":true}},{"k":[7,3,0,15,0],"v":{"l":true,"r":true,"sid":16}},{"k":[6,4,0,15,0],"v":{"hs":0,"sid":16,"ws":1}},{"k":[15,0,0,11,0],"v":{"b":true,"hs":3,"sid":16,"t":true}},{"k":[11,0,0,15,0],"v":{"hs":3,"l":true,"r":true,"sid":16}},{"k":[8,3,0,15,0],"v":{"l":true,"r":true,"sid":16}},{"k":[15,3,0,8,0],"v":{"b":true,"sid":16,"t":true}},{"k":[15,0,0,12,0],"v":{"b":true,"hs":3,"sid":16,"t":true}},{"k":[12,0,0,15,0],"v":{"hs":3,"l":true,"r":true,"sid":16}},{"k":[9,3,0,15,0],"v":{"l":true,"r":true,"sid":16}},{"k":[15,3,0,9,0],"v":{"b":true,"sid":16,"t":true}},{"k":[15,0,0,13,0],"v":{"b":true,"hs":3,"sid":16,"t":true}},{"k":[13,0,0,15,0],"v":{"hs":3,"l":true,"r":true,"sid":16}},{"k":[10,3,0,15,0],"v":{"l":true,"r":true,"sid":16}},{"k":[15,3,0,10,0],"v":{"b":true,"sid":16,"t":true}},{"k":[15,3,0,15,0],"v":{"l":true,"sid":16,"t":true}},{"k":[15,4,0,15,0],"v":{"hs":0,"sid":16,"ws":1}},{"k":[0,0,0,0,0],"v":{"b":true,"hs":3,"r":true,"sid":16}},{"k":[0,0,0,5,0],"v":{"b":true,"hs":3,"r":true,"sid":16,"t":true}},{"k":[5,0,0,0,0],"v":{"hs":3,"l":true,"r":true,"sid":16}},{"k":[1,0,0,4,0],"v":{"sid":16,"t":true}},{"k":[2,3,0,0,0],"v":{"l":true,"r":true,"sid":16}},{"k":[0,3,0,2,0],"v":{"b":true,"sid":16,"t":true}},{"k":[0,0,0,6,0],"v":{"b":true,"hs":3,"sid":16,"t":true}},{"k":[6,0,0,0,0],"v":{"hs":3,"l":true,"r":true,"sid":16}},{"k":[1,0,0,5,0],"v":{"hs":3,"l":true,"r":true,"sid":16}},{"k":[3,3,0,0,0],"v":{"l":true,"r":true,"sid":16}},{"k":[0,3,0,3,0],"v":{"b":true,"sid":16,"t":true}},{"k":[0,0,0,7,0],"v":{"b":true,"hs":3,"sid":16,"t":true}},{"k":[7,0,0,0,0],"v":{"hs":3,"l":true,"r":true,"sid":16}},{"k":[2,0,0,5,0],"v":{"hs":3,"l":true,"r":true,"sid":16}},{"k":[4,3,0,0,0],"v":{"l":true,"r":true,"sid":16}},{"k":[0,3,0,4,0],"v":{"b":true,"sid":16,"t":true}},{"k":[0,0,0,8,0],"v":{"b":true,"hs":3,"sid":16,"t":true}},{"k":[8,0,0,0,0],"v":{"hs":3,"l":true,"r":true,"sid":16}},{"k":[3,0,0,5,0],"v":{"hs":3,"l":true,"r":true,"sid":16}},{"k":[5,3,0,0,0],"v":{"l":true,"r":true,"sid":16}},{"k":[0,3,0,5,0],"v":{"b":true,"r":true,"sid":16,"t":true}},{"k":[0,0,0,1,0],"v":{"b":true,"hs":3,"sid":16,"t":true}},{"k":[1,0,0,0,0],"v":{"hs":3,"l":true,"r":true,"sid":16}},{"k":[0,0,0,2,0],"v":{"b":true,"hs":3,"sid":16,"t":true}},{"k":[2,0,0,0,0],"v":{"hs":3,"l":true,"r":true,"sid":16}},{"k":[1,0,0,1,0],"v":{"b":true,"sid":16}},{"k":[0,0,0,3,0],"v":{"b":true,"hs":3,"sid":16,"t":true}},{"k":[3,0,0,0,0],"v":{"hs":3,"l":true,"r":true,"sid":16}},{"k":[1,0,0,2,0],"v":{"b":true,"sid":16,"t":true}},{"k":[0,3,0,0,0],"v":{"b":true,"r":true,"sid":16}},{"k":[0,0,0,4,0],"v":{"b":true,"hs":3,"sid":16,"t":true}},{"k":[4,0,0,0,0],"v":{"hs":3,"l":true,"r":true,"sid":16}},{"k":[1,0,0,3,0],"v":{"b":true,"sid":16,"t":true}},{"k":[1,3,0,0,0],"v":{"l":true,"r":true,"sid":16}},{"k":[0,3,0,1,0],"v":{"b":true,"sid":16,"t":true}},{"k":[0,4,0,0,0],"v":{"hs":0,"sid":16,"ws":1}},{"k":[0,0,0,13,0],"v":{"b":true,"hs":3,"sid":16,"t":true}},{"k":[13,0,0,0,0],"v":{"hs":3,"l":true,"r":true,"sid":16}},{"k":[10,0,0,3,0],"v":{"b":true,"hs":3,"sid":16,"t":true}},{"k":[6,0,0,7,0],"v":{"b":true,"hs":3,"sid":16,"t":true}},{"k":[10,3,0,0,0],"v":{"b":true,"l":true,"r":true,"sid":16}},{"k":[0,3,0,10,0],"v":{"b":true,"sid":16,"t":true}},{"k":[5,3,0,5,0],"v":{"l":true,"r":true,"sid":16}},{"k":[0,0,0,14,0],"v":{"b":true,"hs":3,"sid":16,"t":true}},{"k":[14,0,0,0,0],"v":{"hs":3,"l":true,"r":true,"sid":16}},{"k":[10,0,0,4,0],"v":{"b":true,"hs":3,"sid":16,"t":true}},{"k":[6,0,0,8,0],"v":{"b":true,"hs":3,"sid":16,"t":true}},{"k":[11,3,0,0,0],"v":{"l":true,"r":true,"sid":16}},{"k":[10,3,0,1,0],"v":{"b":true,"sid":16,"t":true}},{"k":[0,3,0,11,0],"v":{"b":true,"sid":16,"t":true}},{"k":[6,3,0,5,0],"v":{"b":true,"l":true,"r":true,"sid":16}},{"k":[10,4,0,0,0],"v":{"hs":0,"sid":16,"ws":1}},{"k":[0,0,0,15,0],"v":{"hs":3,"r":true,"sid":16,"t":true}},{"k":[15,0,0,0,0],"v":{"b":true,"hs":3,"l":true,"sid":16}},{"k":[10,0,0,5,0],"v":{"b":true,"hs":3,"sid":16,"t":true}},{"k":[6,0,0,9,0],"v":{"hs":3,"sid":16,"t":true}},{"k":[12,3,0,0,0],"v":{"l":true,"r":true,"sid":16}},{"k":[10,3,0,2,0],"v":{"b":true,"sid":16,"t":true}},{"k":[0,3,0,12,0],"v":{"b":true,"sid":16,"t":true}},{"k":[6,3,0,6,0],"v":{"b":true,"sid":16,"t":true}},{"k":[7,3,0,5,0],"v":{"l":true,"sid":16}},{"k":[6,4,0,5,0],"v":{"hs":0,"r":true,"sid":16,"ws":1}},{"k":[15,0,0,1,0],"v":{"b":true,"hs":3,"sid":16,"t":true}},{"k":[1,0,0,15,0],"v":{"hs":3,"l":true,"r":true,"sid":16}},{"k":[10,0,0,6,0],"v":{"hs":3,"r":true,"sid":16,"t":true}},{"k":[13,3,0,0,0],"v":{"l":true,"r":true,"sid":16}},{"k":[10,3,0,3,0],"v":{"b":true,"sid":16,"t":true}},{"k":[0,3,0,13,0],"v":{"b":true,"sid":16,"t":true}},{"k":[6,3,0,7,0],"v":{"b":true,"sid":16,"t":true}},{"k":[7,4,0,5,0],"v":{"hs":0,"l":true,"sid":16,"ws":1}},{"k":[0,0,0,9,0],"v":{"b":true,"hs":3,"sid":16,"t":true}},{"k":[9,0,0,0,0],"v":{"hs":3,"l":true,"r":true,"sid":16}},{"k":[4,0,0,5,0],"v":{"hs":3,"l":true,"r":true,"sid":16}},{"k":[1,0,0,8,0],"v":{"b":true,"sid":17}},{"k":[6,3,0,0,0],"v":{"l":true,"r":true,"sid":16}},{"k":[0,3,0,6,0],"v":{"b":true,"sid":16,"t":true}},{"k":[1,3,0,5,0],"v":{"l":true,"r":true,"sid":16}},{"k":[0,4,0,5,0],"v":{"hs":0,"sid":16,"ws":1}},{"k":[0,0,0,10,0],"v":{"b":true,"hs":3,"sid":16,"t":true}},{"k":[10,0,0,0,0],"v":{"b":true,"hs":3,"l":true,"r":true,"sid":16}},{"k":[5,0,0,5,0],"v":{"hs":3,"l":true,"r":true,"sid":16}},{"k":[1,0,0,9,0],"v":{"sid":17,"t":true}},{"k":[7,3,0,0,0],"v":{"l":true,"r":true,"sid":16}},{"k":[0,3,0,7,0],"v":{"b":true,"sid":16,"t":true}},{"k":[2,3,0,5,0],"v":{"l":true,"r":true,"sid":16}},{"k":[0,0,0,11,0],"v":{"b":true,"hs":3,"sid":16,"t":true}},{"k":[11,0,0,0,0],"v":{"hs":3,"l":true,"r":true,"sid":16}},{"k":[10,0,0,1,0],"v":{"b":true,"hs":3,"sid":16,"t":true}},{"k":[6,0,0,5,0],"v":{"b":true,"hs":3,"l":true,"r":true,"sid":16}},{"k":[8,3,0,0,0],"v":{"l":true,"r":true,"sid":16}},{"k":[0,3,0,8,0],"v":{"b":true,"sid":16,"t":true}},{"k":[3,3,0,5,0],"v":{"l":true,"r":true,"sid":16}},{"k":[0,0,0,12,0],"v":{"b":true,"hs":3,"sid":16,"t":true}},{"k":[12,0,0,0,0],"v":{"hs":3,"l":true,"r":true,"sid":16}},{"k":[10,0,0,2,0],"v":{"b":true,"hs":3,"sid":16,"t":true}},{"k":[7,0,0,5,0],"v":{"hs":3,"l":true,"sid":16}},{"k":[6,0,0,6,0],"v":{"b":true,"hs":3,"sid":16,"t":true}},{"k":[9,3,0,0,0],"v":{"l":true,"r":true,"sid":16}},{"k":[0,3,0,9,0],"v":{"b":true,"sid":16,"t":true}},{"k":[4,3,0,5,0],"v":{"l":true,"r":true,"sid":16}},{"k":[15,0,0,6,0],"v":{"b":true,"hs":3,"sid":16,"t":true}},{"k":[6,0,0,15,0],"v":{"hs":3,"l":true,"r":true,"sid":16,"t":true}},{"k":[15,3,0,3,0],"v":{"b":true,"sid":16,"t":true}},{"k":[12,3,0,6,0],"v":{"l":true,"sid":16}},{"k":[3,3,0,15,0],"v":{"l":true,"r":true,"sid":16}},{"k":[6,3,0,12,0],"v":{"b":true,"sid":16}},{"k":[15,0,0,7,0],"v":{"b":true,"hs":3,"sid":16,"t":true}},{"k":[7,0,0,15,0],"v":{"hs":3,"l":true,"r":true,"sid":16}},{"k":[15,3,0,4,0],"v":{"b":true,"sid":16,"t":true}},{"k":[4,3,0,15,0],"v":{"l":true,"r":true,"sid":16}},{"k":[6,3,0,13,0],"v":{"b":true,"sid":16,"t":true}},{"k":[12,4,0,6,0],"v":{"hs":0,"sid":16,"ws":1}},{"k":[6,4,0,12,0],"v":{"hs":0,"sid":16,"ws":1}},{"k":[15,0,0,8,0],"v":{"b":true,"hs":3,"sid":16,"t":true}},{"k":[8,0,0,15,0],"v":{"hs":3,"l":true,"r":true,"sid":16}},{"k":[15,3,0,5,0],"v":{"b":true,"sid":16,"t":true}},{"k":[5,3,0,15,0],"v":{"l":true,"r":true,"sid":16}},{"k":[6,3,0,14,0],"v":{"b":true,"sid":16,"t":true}},{"k":[15,0,0,9,0],"v":{"b":true,"hs":3,"sid":16,"t":true}},{"k":[9,0,0,15,0],"v":{"hs":3,"l":true,"r":true,"sid":16}},{"k":[15,3,0,6,0],"v":{"b":true,"sid":16,"t":true}},{"k":[6,3,0,15,0],"v":{"l":true,"r":true,"sid":16,"t":true}},{"k":[15,0,0,2,0],"v":{"b":true,"hs":3,"sid":16,"t":true}},{"k":[2,0,0,15,0],"v":{"hs":3,"l":true,"r":true,"sid":16}},{"k":[11,0,0,6,0],"v":{"hs":3,"l":true,"r":true,"sid":16}},{"k":[14,3,0,0,0],"v":{"l":true,"r":true,"sid":16}},{"k":[10,3,0,4,0],"v":{"b":true,"sid":16,"t":true}},{"k":[0,3,0,14,0],"v":{"b":true,"sid":16,"t":true}},{"k":[6,3,0,8,0],"v":{"b":true,"sid":16,"t":true}},{"k":[15,0,0,3,0],"v":{"b":true,"hs":3,"sid":16,"t":true}},{"k":[3,0,0,15,0],"v":{"hs":3,"l":true,"r":true,"sid":16}},{"k":[12,0,0,6,0],"v":{"hs":3,"l":true,"sid":16}},{"k":[6,0,0,12,0],"v":{"b":true,"hs":3,"sid":16}},{"k":[15,3,0,0,0],"v":{"b":true,"l":true,"sid":16}},{"k":[10,3,0,5,0],"v":{"b":true,"sid":16,"t":true}},{"k":[0,3,0,15,0],"v":{"r":true,"sid":16,"t":true}},{"k":[6,3,0,9,0],"v":{"sid":16,"t":true}},{"k":[15,0,0,4,0],"v":{"b":true,"hs":3,"sid":16,"t":true}},{"k":[4,0,0,15,0],"v":{"hs":3,"l":true,"r":true,"sid":16}},{"k":[6,0,0,13,0],"v":{"b":true,"hs":3,"sid":16,"t":true}},{"k":[15,3,0,1,0],"v":{"b":true,"sid":16,"t":true}},{"k":[10,3,0,6,0],"v":{"r":true,"sid":16,"t":true}},{"k":[1,3,0,15,0],"v":{"l":true,"r":true,"sid":16}},{"k":[0,4,0,15,0],"v":{"hs":0,"sid":16,"ws":1}},{"k":[15,4,0,0,0],"v":{"hs":0,"sid":16,"ws":1}},{"k":[6,4,0,9,0],"v":{"hs":0,"sid":16,"ws":1}},{"k":[15,0,0,5,0],"v":{"b":true,"hs":3,"sid":16,"t":true}},{"k":[5,0,0,15,0],"v":{"hs":3,"l":true,"r":true,"sid":16}},{"k":[6,0,0,14,0],"v":{"b":true,"hs":3,"sid":16,"t":true}},{"k":[15,3,0,2,0],"v":{"b":true,"sid":16,"t":true}},{"k":[11,3,0,6,0],"v":{"l":true,"r":true,"sid":16}},{"k":[2,3,0,15,0],"v":{"l":true,"r":true,"sid":16}},{"k":[10,4,0,6,0],"v":{"hs":0,"sid":16,"ws":1}}],"o":[]},"objs":{"list":[{"k":[2,0,0,2,0],"v":{"events":[{"id":2,"name":"Hero touch","p":[],"r":{"1":{"bh":true,"c":[{"command":[8,"",-1,0,0,1,"НЕ МЕШАЙ Я ЖРАТЬ ГОТОВЛЮ"],"kind":1}]}},"sys":false}],"hId":-1,"id":4,"name":"OBJ0004","ooepf":false,"states":[{"cam":true,"climb":false,"dir":false,"gid":26,"gk":4,"id":1,"move":true,"name":"Состояние 1","pix":true,"pos":false,"stop":false,"sx":{"k":12,"v":1},"sy":{"k":12,"v":1},"sz":{"k":12,"v":1},"through":false,"x":0,"y":0}]}},{"k":[2,0,0,11,0],"v":{"events":[{"id":2,"name":"Hero touch","p":[],"r":{"1":{"bh":true,"c":[{"command":[8,"",-1,0,0,1,"ЖРААААТЬ"],"kind":1}]}},"sys":false}],"hId":-1,"id":3,"name":"OBJ0003","ooepf":false,"states":[{"cam":true,"climb":false,"dir":false,"gid":54,"gk":4,"id":1,"move":true,"name":"Состояние 1","omk":1,"pix":true,"pos":false,"s":3,"stop":false,"sx":{"k":12,"v":1},"sy":{"k":12,"v":1},"sz":{"k":12,"v":1},"through":false,"x":0,"y":0}]}},{"k":[11,0,0,5,0],"v":{"events":[{"id":2,"name":"Hero touch","p":[],"r":{"1":{"bh":true,"c":[{"command":[8,"",-1,0,0,1,"секретка!"],"kind":1}]}},"sys":false}],"hId":-1,"id":6,"name":"OBJ0006","ooepf":false,"states":[{"cam":true,"climb":false,"dir":false,"gid":13,"gk":4,"id":1,"move":true,"name":"Состояние 1","pix":true,"pos":false,"stop":false,"sx":{"k":12,"v":1},"sy":{"k":12,"v":1},"sz":{"k":12,"v":1},"through":false,"x":0,"y":0}]}},{"k":[13,0,0,12,0],"v":{"hId":2,"id":2,"name":"Герой","ooepf":false}},{"k":[10,0,0,14,0],"v":{"events":[{"id":2,"name":"Hero touch","p":[],"r":{"1":{"bh":true,"c":[{"command":[7,0,0,1,3,0,0,9,0,0,0],"kind":20}]}},"sys":false}],"hId":-1,"id":1,"name":"OBJ0001","ooepf":false,"states":[{"cam":true,"climb":false,"dir":false,"gid":-1,"gk":0,"id":1,"move":true,"name":"Состояние 1","pix":true,"pos":false,"stop":false,"sx":{"k":12,"v":1},"sy":{"k":12,"v":1},"sz":{"k":12,"v":1},"through":false,"x":0,"y":0}]}},{"k":[9,0,0,10,0],"v":{"events":[{"id":2,"name":"Hero touch","p":[],"r":{"1":{"bh":true,"c":[{"command":[8,"",-1,0,0,1,"...я каменъ"],"kind":1}]}},"sys":false}],"hId":-1,"id":5,"name":"OBJ0005","ooepf":false,"states":[{"cam":true,"climb":false,"dir":false,"gid":65,"gk":4,"id":1,"move":true,"name":"Состояние 1","omk":1,"pix":true,"pos":false,"s":5,"stop":false,"sx":{"k":12,"v":1},"sy":{"k":12,"v":1},"sz":{"k":12,"v":1},"through":false,"x":0,"y":0}]}}]},"objs3d":{"a":[{"k":[4,0,0,1,0],"v":{"did":16}},{"k":[1,0,0,4,0],"v":{"did":103}},{"k":[4,0,0,2,0],"v":{"did":16}},{"k":[5,0,0,1,0],"v":{"did":16}},{"k":[5,0,0,2,0],"v":{"did":16}},{"k":[6,0,0,1,0],"v":{"did":16}},{"k":[1,0,0,6,0],"v":{"did":99}},{"k":[4,0,0,3,0],"v":{"did":97}},{"k":[6,0,0,2,0],"v":{"did":16}},{"k":[1,0,0,1,0],"v":{"did":103}},{"k":[1,0,0,2,0],"v":{"did":103}},{"k":[1,0,0,3,0],"v":{"did":103}},{"k":[6,0,0,7,0],"v":{"did":107}},{"k":[7,0,0,6,0],"v":{"did":107}},{"k":[6,0,0,3,0,0,50,0],"v":{"did":97}},{"k":[1,0,0,13,0],"v":{"did":82}},{"k":[14,0,0,1,0],"v":{"did":106}},{"k":[3,0,0,6,0],"v":{"did":98}},{"k":[4,0,0,6,0],"v":{"did":99}},{"k":[7,0,0,3,0],"v":{"did":97}},{"k":[11,0,0,1,0],"v":{"did":105}},{"k":[8,0,0,14,0],"v":{"did":97}},{"k":[10,0,0,7,0],"v":{"did":88}}],"o":[]},"sprites":{"list":[{"k":[12,0,0,7,0,43.75,68.75,0],"v":{"k":7,"t":[4,7,1,3]}},{"k":[12,0,0,7,0,50,62.5,0],"v":{"k":7,"t":[4,7,1,3]}},{"k":[12,0,0,7,0,31.25,43.75,0],"v":{"k":7,"t":[4,7,1,3]}},{"k":[14,0,0,11,0],"v":{"k":4,"t":[2,8,1,2]}},{"k":[12,0,0,7,0,50,56.25,0],"v":{"k":6,"t":[4,7,1,3]}},{"k":[12,0,0,7,0,37.5,68.75,0],"v":{"k":7,"t":[4,7,1,3]}},{"k":[12,0,0,7,0,43.75,62.5,0],"v":{"k":7,"t":[4,7,1,3]}},{"k":[1,1,0,3,0],"v":{"k":4,"t":[4,6,1,1]}},{"k":[1,1,0,4,0],"v":{"f":false,"k":4,"t":[5,6,1,1]}},{"k":[12,0,0,7,0,43.75,43.75,0],"v":{"k":6,"t":[4,7,1,3]}},{"k":[12,0,0,7,0,37.5,50,0],"v":{"k":6,"t":[4,7,1,3]}},{"k":[12,0,0,7,0,50,68.75,0],"v":{"k":7,"t":[4,7,1,3]}},{"k":[1,0,0,7,0],"v":{"k":4,"t":[2,8,1,2]}},{"k":[1,1,0,1,0],"v":{"k":4,"t":[7,6,1,1]}},{"k":[3,0,0,1,0],"v":{"k":4,"t":[4,7,1,3]}},{"k":[1,1,0,2,0],"v":{"k":4,"t":[0,6,1,1]}},{"k":[1,0,0,12,0],"v":{"f":false,"k":4,"t":[0,2,1,2]}},{"k":[3,0,0,6,0,50,56.25,0],"v":{"k":5,"t":[6,8,1,2]}},{"k":[8,0,0,1,0],"v":{"k":4,"t":[4,7,1,3]}},{"k":[1,1,0,8,0],"v":{"k":4,"t":[4,11,1,1]}},{"k":[10,0,0,14,0,50,93.75,0],"v":{"f":false,"k":5,"t":[4,7,1,2]}},{"k":[1,1,0,9,0],"v":{"k":4,"t":[5,10,1,1]}},{"k":[1,0,0,10,0],"v":{"k":4,"t":[1,11,1,1]}},{"k":[5,0,0,7,0],"v":{"k":4,"t":[2,8,1,2]}},{"k":[12,0,0,7,0,50,43.75,0],"v":{"k":6,"t":[4,7,1,3]}},{"k":[12,0,0,7,0,37.5,56.25,0],"v":{"k":7,"t":[4,7,1,3]}},{"k":[12,0,0,7,0,43.75,50,0],"v":{"k":7,"t":[4,7,1,3]}},{"k":[9,0,0,14,0,56.25,93.75,0],"v":{"f":false,"k":5,"t":[2,1,1,1]}},{"k":[3,0,0,14,0],"v":{"f":false,"k":4,"t":[1,2,1,2]}},{"k":[3,0,0,15,0],"v":{"f":false,"k":4,"t":[1,2,1,2]}},{"k":[12,0,0,7,0],"v":{"k":6,"t":[4,7,1,3]}},{"k":[12,0,0,7,0,37.5,62.5,0],"v":{"k":7,"t":[4,7,1,3]}},{"k":[12,0,0,7,0,43.75,56.25,0],"v":{"k":7,"t":[4,7,1,3]}},{"k":[12,0,0,7,0,37.5,43.75,0],"v":{"k":6,"t":[4,7,1,3]}}],"overflow":[],"walls":[]}}